{
    "backend": "flask",
    "db_name": "",
    "db_pass": "",
    "db_type": "",
    "db_user": "",
    "dbms": "0",
    "description": "generated product",
    "design": "soft-ui-dashboard",
    "docker": "0",
    "err_code": 0,
    "frontend": "",
    "heroku": "0",
    "pattern": "mvc",
    "pro": "0",
    "task_id": "6bed6c24-c7d6-4630-a1da-e65196c55534",
    "task_info": "Upload Sources [0%] - 319 files",
    "task_output": "6bed6c24-c7d6-4630-a1da-e65196c55534.zip",
    "task_result": "SUCCESS",
    "task_state": "RUNNING",
    "task_ts_end": "2024-09-02-03-33-38",
    "task_ts_start": "2024-09-02-03-33-35"
}